{
	"animations": [
		{
			"offsets": [
				0,
				0
			],
			"loop": false,
			"fps": 24,
			"anim": "singLEFT",
			"indices": [],
			"name": "Left"
		},
		{
			"offsets": [
				0,
				0
			],
			"loop": false,
			"fps": 24,
			"anim": "singDOWN",
			"indices": [],
			"name": "Down"
		},
		{
			"offsets": [
				0,
				0
			],
			"loop": false,
			"fps": 24,
			"anim": "singUP",
			"indices": [],
			"name": "Up"
		},
		{
			"offsets": [
				0,
				0
			],
			"loop": false,
			"fps": 24,
			"anim": "singRIGHT",
			"indices": [],
			"name": "Right"
		},
		{
			"offsets": [
				-1,
				0
			],
			"loop": false,
			"fps": 24,
			"anim": "idle",
			"indices": [],
			"name": "Idle"
		}
	],
	"no_antialiasing": true,
	"image": "characters/SoullessEndeavoursGaming",
	"position": [
		0,
		-80
	],
	"healthicon": "duke-pixel",
	"flip_x": false,
	"healthbar_colors": [
		214,
		25,
		82
	],
	"camera_position": [
		-760,
		-610
	],
	"sing_duration": 6.1,
	"scale": 4.95
}